uao/__init__.py
uao/b2u.py
uao/u2b.py
uao-0.2.0.dist-info/LICENSE
uao-0.2.0.dist-info/METADATA
uao-0.2.0.dist-info/WHEEL
uao-0.2.0.dist-info/top_level.txt
uao-0.2.0.dist-info/zip-safe
uao-0.2.0.dist-info/RECORD
