Metadata-Version: 2.1
Name: uao
Version: 0.2.0
Summary: Big5-UAO encoder/decoder in pure Python
Home-page: https://github.com/eight04/pyUAO
Author: eight
Author-email: eight04@gmail.com
License: MIT
Keywords: encoding,uao,big5
Platform: UNKNOWN
Classifier: Development Status :: 4 - Beta
Classifier: Intended Audience :: Developers
Classifier: License :: OSI Approved :: MIT License
Classifier: Natural Language :: Chinese (Traditional)
Classifier: Programming Language :: Python :: 2
Classifier: Programming Language :: Python :: 2.7
Classifier: Programming Language :: Python :: 3
Classifier: Programming Language :: Python :: 3.6
Classifier: Programming Language :: Python :: 3.7
Classifier: Programming Language :: Python :: 3.8
Classifier: Programming Language :: Python :: 3.9
Classifier: Topic :: Software Development :: Libraries
Classifier: Topic :: Text Processing
